pyaipersonality/__init__.py
pyaipersonality/binding.py
pyaipersonality/langchain_integration.py
pyaipersonality/lllm_server.py
pyaipersonality/server.py
pyaipersonality-1.0.1.dist-info/LICENSE
pyaipersonality-1.0.1.dist-info/METADATA
pyaipersonality-1.0.1.dist-info/WHEEL
pyaipersonality-1.0.1.dist-info/entry_points.txt
pyaipersonality-1.0.1.dist-info/top_level.txt
pyaipersonality-1.0.1.dist-info/RECORD
