Metadata-Version: 2.1
Name: pyaipersonality
Version: 1.0.1
Summary: A python library for AI personality definition
Home-page: https://github.com/ParisNeo/PyAIPersonality
Author: Saifeddine ALOUI
Author-email: aloui.saifeddine@gmail.com
Classifier: Programming Language :: Python :: 3.8
Classifier: License :: OSI Approved :: Apache Software License
Classifier: Operating System :: OS Independent
License-File: LICENSE
Requires-Dist: tqdm
Requires-Dist: pyyaml
Requires-Dist: Pillow
Requires-Dist: flask
Requires-Dist: flask-socketio
Requires-Dist: flask-cors
Requires-Dist: simple-websocket
Provides-Extra: dev
Requires-Dist: tqdm ; extra == 'dev'
Requires-Dist: pyyaml ; extra == 'dev'
Requires-Dist: Pillow ; extra == 'dev'
Requires-Dist: flask ; extra == 'dev'
Requires-Dist: flask-socketio ; extra == 'dev'
Requires-Dist: flask-cors ; extra == 'dev'
Requires-Dist: simple-websocket ; extra == 'dev'
